{
  "$schema": "https://schema.management.azure.com/schemas/2019-04-01/deploymentParameters.json#",
  "contentVersion": "1.0.0.0",
  "parameters": {
    "existingVNETName": {
      "value": "DemoRG01-vnet"
    },
    "existingSubnetName": {
      "value": "default"
    },
    "vmSize": {
      "value": "Standard_F2s_v2"
    },
    "domainToJoin": {
      "value": "shaikyaseen.com"
    },
    "domainUsername": {
      "value": "azuerUser"
    },
    "domainPassword": {
      "value": "P@ssword!"
    },
    "domainJoinOptions": {
      "value": 3
    },
    "vmAdminUsername": {
      "value": "azureUser"
    },
    "vmAdminPassword": {
      "value": "P@ssword!"
    },
    "dnsLabelPrefix": {
      "value": "GEN-UNIQUE" 
    }
  }
}